{
  "singleTarget": true,
  "name": "Suppression",
  "lightRadius": 300,
  "type": "legs",
  "speed": 0.40,
  "hitSize": 110,
  "health": 5300000,
  "legCount": 6,
  "drownTimeMultiplier": 99999999999999,
  "canDrown": false,
  "groundLayer": 87,
  "legPairOffset": 2,
  "outlineColor": "1d1c1a",
  "legLength": 178,
  "legBaseOffset": 54,
  "legExtension": -20,
  "legContinuousMove": true,
  "allowLegStep": true,
  "legSpeed": 0.7,
  "legLengthScl": 1,
  "rippleScale": 9,
  "legSplashDamage": 700,
  "legSplashRange": 95,
  "allowLegStep": true,
  "hovering": true,
  "armor": 460,
  "drag": 0.2,
  "range": 450,
  "maxRange": 2000,
  "flying": false,
  "rotateSpeed": 1.5,
  "immunities": [
    "tarred",
    "melting",
    "corroded",
    "freezing",
    "blasted",
    "slow",
    "burning",
    "wet",
    "muddy",
    "sapped",
    "disarmed",
    "shocked",
    "electrified",
    "spore-slowed"
  ],
}
"abilities": [
    {
      "type": "mindustry.entities.abilities.RepairFieldAbility",
      "activeEffect": [
        {
        "type": "WaveEffect",
        "lifetime": 35,
        "sizeFrom": 0,
        "sizeTo": 120,
        "sides": 4,
        "strokeFrom": 3,
        "strokeTo": 0,
        "lightColor": "D7FFB8FF",
        "colorFrom": "D7FFB8FF",
        "colorTo": "D7FFB8FF"
      },
      ]
      "healEffect": {
        "type": "WaveEffect",
        "lifetime": 35,
        "sizeFrom": 0,
        "sizeTo": 10,
        "strokeFrom": 2,
        "strokeTo": 0,
        "lightColor": "D7FFB8FF",
        "colorFrom": "D7FFB8FF",
        "colorTo": "D7FFB8FF"
      },
      "range": 120,
      "amount": 50,
      "reload": 230
    }
  {
      "type": "mindustry.entities.abilities.RepairFieldAbility",
      "activeEffect": [
        {
        "type": "WaveEffect",
        "lifetime": 35,
        "sizeFrom": 0,
        "sizeTo": 120,
        "sides": 4,
        "strokeFrom": 3,
        "strokeTo": 0,
        "lightColor": "D7FFB8FF",
        "colorFrom": "D7FFB8FF",
        "colorTo": "D7FFB8FF"
      },
      ]
      "healEffect": {
        "type": "WaveEffect",
        "lifetime": 35,
        "sizeFrom": 0,
        "sizeTo": 10,
        "strokeFrom": 2,
        "strokeTo": 0,
        "lightColor": "D7FFB8FF",
        "colorFrom": "D7FFB8FF",
        "colorTo": "D7FFB8FF"
      },
      "range": 150,
      "amount": 50,
      "reload": 230
    }
  {
      "type": "mindustry.entities.abilities.RepairFieldAbility",
      "activeEffect": [
        {
        "type": "WaveEffect",
        "lifetime": 35,
        "sizeFrom": 0,
        "sizeTo": 120,
        "sides": 4,
        "strokeFrom": 3,
        "strokeTo": 0,
        "lightColor": "D7FFB8FF",
        "colorFrom": "D7FFB8FF",
        "colorTo": "D7FFB8FF"
      },
      ]
      "healEffect": {
        "type": "WaveEffect",
        "lifetime": 35,
        "sizeFrom": 0,
        "sizeTo": 10,
        "strokeFrom": 2,
        "strokeTo": 0,
        "lightColor": "D7FFB8FF",
        "colorFrom": "D7FFB8FF",
        "colorTo": "D7FFB8FF"
      },
      "range": 200,
      "amount": 50,
      "reload": 230
    }
  ]
}
